{"405gzo1m64neik4":[{"n":"Room Layout","t":"starter","i":["0-164"],"a":14,"b":10,"z":0}],"405gzo1m65vl5zo":[{"n":"lava lamp","t":"interior","i":["0-7"],"a":1,"b":3}],"405gzm1m6omkza3":[{"n":"grass","t":"starter","i":["165"],"a":0,"b":0}],"405gzo1m6uu4yqb":[{"n":"house","t":"houses","i":["0-55"],"a":6,"b":7}],"405gzo1m6uu4yqh":[{"n":"house","t":"houses","i":["56-111"],"a":6,"b":7}],"405gzo1m6uu4yqp":[{"n":"house","t":"houses","i":["112-243"],"a":10,"b":11}],"405gzo1m6uu4yqs":[{"n":"house","t":"houses","i":["244-298"],"a":4,"b":10}],"405gzo1m6uu4yqv":[{"n":"house","t":"houses","i":["299-368"],"a":6,"b":9}],"405gzo1m6uu4yqz":[{"n":"house","t":"houses","i":["369-536"],"a":13,"b":11}],"405gzo1m6uu4yrd":[{"n":"house","t":"houses","i":["537-746"],"a":13,"b":14}],"405gzo1m6uu4yrp":[{"n":"house","t":"houses","i":["747-810"],"a":7,"b":7}],"405gzo1m6uu4yrq":[{"n":"house","t":"houses","i":["811-842"],"a":3,"b":7}],"405gzo1m6uu4yrw":[{"n":"house","t":"houses","i":["843-941"],"a":8,"b":10}],"405gzo1m6uu4yrz":[{"n":"house","t":"houses","i":["942-1037"],"a":7,"b":11}],"405gzo1m6uu4ys2":[{"n":"house","t":"houses","i":["1038-1091"],"a":5,"b":8}],"405gzo1m6uu4ys3":[{"n":"house","t":"houses","i":["1092-1139"],"a":5,"b":7}],"405gzo1m6uu4ys4":[{"n":"house","t":"houses","i":["1140-1193"],"a":5,"b":8}],"405gzo1m6uu4ys8":[{"n":"house","t":"houses","i":["1194-1241"],"a":5,"b":7}],"405gzo1m6uu4ysg":[{"n":"house","t":"houses","i":["1242-1361"],"a":11,"b":9}],"405gzo1m6uu4ysj":[{"n":"house","t":"houses","i":["1362-1445"],"a":6,"b":11}],"405gzo1m6uu4yso":[{"n":"house","t":"houses","i":["1446-1565"],"a":9,"b":11}],"405gzo1m6uub59e":[{"n":"flower","t":"flowers","i":["0-3"],"a":1,"b":1}],"405gzo1m6uub59g":[{"n":"flower","t":"flowers","i":["4-7"],"a":1,"b":1}],"405gzo1m6uub59h":[{"n":"flower","t":"flowers","i":["8-11"],"a":1,"b":1}],"405gzo1m6uub59i":[{"n":"flower","t":"flowers","i":["12-15"],"a":1,"b":1}],"405gzo1m6uub59j":[{"n":"flower","t":"flowers","i":["16-19"],"a":1,"b":1}],"405gzo1m6uub59k":[{"n":"flower","t":"flowers","i":["20-23"],"a":1,"b":1}],"405gzo1m6uub59l":[{"n":"flower","t":"flowers","i":["24-27"],"a":1,"b":1}],"405gzo1m6uub59m":[{"n":"flower","t":"flowers","i":["28-31"],"a":1,"b":1}],"405gzo1m6uub59n":[{"n":"flower","t":"flowers","i":["32-35"],"a":1,"b":1}],"405gzo1m6uub59o":[{"n":"flower","t":"flowers","i":["36-39"],"a":1,"b":1}],"405gzo1m6uub59p":[{"n":"flower","t":"flowers","i":["40-43"],"a":1,"b":1}],"405gzo1m6uub59q":[{"n":"flower","t":"flowers","i":["44-47"],"a":1,"b":1}],"405gzo1m6uub59r":[{"n":"flower","t":"flowers","i":["48-51"],"a":1,"b":1}],"405gzo1m6uub59s":[{"n":"flower","t":"flowers","i":["52-55"],"a":1,"b":1}],"405gzo1m6uub59t":[{"n":"flower","t":"flowers","i":["56-59"],"a":1,"b":1}],"405gzo1m6uub59u":[{"n":"flower","t":"flowers","i":["60-63"],"a":1,"b":1}],"405gzo1m6uub59v":[{"n":"flower","t":"flowers","i":["64-67"],"a":1,"b":1}],"405gzo1m6uub59w":[{"n":"flower","t":"flowers","i":["68-71"],"a":1,"b":1}],"405gzo1m6uub59x":[{"n":"flower","t":"flowers","i":["72-75"],"a":1,"b":1}],"405gzo1m6uub59y":[{"n":"flower","t":"flowers","i":["76-79"],"a":1,"b":1}],"405gzo1m6uub59z":[{"n":"flower","t":"flowers","i":["80-83"],"a":1,"b":1}],"405gzo1m6uub5a0":[{"n":"flower","t":"flowers","i":["84-87"],"a":1,"b":1}],"405gzo1m6uub5a1":[{"n":"flower","t":"flowers","i":["88-91"],"a":1,"b":1}],"405gzo1m6uub5a2":[{"n":"flower","t":"flowers","i":["92-95"],"a":1,"b":1}],"405gzo1m6uuc0o1":[{"n":"light","t":"lighting","i":["0-5"],"a":1,"b":2}],"405gzo1m6uuc0o2":[{"n":"light","t":"lighting","i":["6-11"],"a":1,"b":2}],"405gzo1m6uuc0o3":[{"n":"light","t":"lighting","i":["12-17"],"a":1,"b":2}],"405gzo1m6uuccdn":[{"n":"statue","t":"statues","i":["0-7"],"a":1,"b":3}],"405gzo1m6uuda2l":[{"n":"crate","t":"crates","i":["0-3"],"a":1,"b":1}],"405gzo1m6uuda2m":[{"n":"crate","t":"crates","i":["4-7"],"a":1,"b":1}],"405gzo1m6uuda2n":[{"n":"crate","t":"crates","i":["8-11"],"a":1,"b":1}],"405gzo1m6uuda2o":[{"n":"crate","t":"crates","i":["12-15"],"a":1,"b":1}],"405gzo1m6uuda2p":[{"n":"crate","t":"crates","i":["16-19"],"a":1,"b":1}],"405gzo1m6uuda2q":[{"n":"crate","t":"crates","i":["20-23"],"a":1,"b":1}],"405gzo1m6uuda2r":[{"n":"crate","t":"crates","i":["24-27"],"a":1,"b":1}],"405gzo1m6uudoh3":[{"n":"bench","t":"seating","i":["0-3"],"a":1,"b":1}],"405gzo1m6uuf988":[{"n":"sign post","t":"signs","i":["0-5"],"a":1,"b":2}],"405gzo1m6uuf989":[{"n":"sign post","t":"signs","i":["6-11"],"a":1,"b":2}],"405gzo1m6uuf98a":[{"n":"sign post","t":"signs","i":["12-17"],"a":1,"b":2}],"405gzo1m6uuf98b":[{"n":"sign post","t":"signs","i":["18-23"],"a":1,"b":2}],"405gzo1m6uuf98c":[{"n":"sign post","t":"signs","i":["24-27"],"a":1,"b":1}],"405gzo1m6uuf992":[{"n":"flower","t":"flowers","i":["96-101"],"a":1,"b":2}],"405gzo1m6uuf99j":[{"n":"fire","t":"fire","i":["0-5"],"a":1,"b":2}],"405gzo1m6uuf99x":[{"n":"chest","t":"chests","i":["0-3"],"a":1,"b":1}],"405gzo1m6uuf99y":[{"n":"chest","t":"chests","i":["4-7"],"a":1,"b":1}],"405gzo1m6uufqn8":[{"n":"mailbox","t":"mailboxes","i":["0-3"],"a":1,"b":1}],"405gzo1m6uufqn9":[{"n":"mailbox","t":"mailboxes","i":["4-7"],"a":1,"b":1}],"405gzo1m6uufqna":[{"n":"mailbox","t":"mailboxes","i":["8-11"],"a":1,"b":1}],"405gzo1m6uufqnb":[{"n":"mailbox","t":"mailboxes","i":["12-15"],"a":1,"b":1}],"405gzo1m6uuggda":[{"n":"tree","t":"tree","i":["0-5"],"a":1,"b":2}],"405gzo1m6uuggdn":[{"n":"wood","t":"wood","i":["0-3"],"a":1,"b":1}],"405gzo1m6uuggdo":[{"n":"wood","t":"wood","i":["4-7"],"a":1,"b":1}],"405gzo1m6uuggdp":[{"n":"wood","t":"wood","i":["8-11"],"a":1,"b":1}],"405gzo1m6uuggdq":[{"n":"chopping block","t":"wood","i":["12-15"],"a":1,"b":1}],"405gzo1m6uuh6td":[{"n":"rail","t":"rail","i":["0-5"],"a":2,"b":1}],"405gzo1m6uuh6te":[{"n":"rail","t":"rail","i":["6-9"],"a":1,"b":1}],"405gzo1m6uulua4":[{"n":"tree","t":"tree","i":["6-7"],"a":0,"b":1}],"405gzo1m6uulua5":[{"n":"tree","t":"tree","i":["8-13"],"a":1,"b":2}],"405gzo1m6uulua6":[{"n":"tree","t":"tree","i":["14-25"],"a":2,"b":3}],"405gzo1m6uulua7":[{"n":"tree","t":"tree","i":["26-40"],"a":2,"b":4}],"405gzo1m6uulua8":[{"n":"tree","t":"tree","i":["41-52"],"a":2,"b":3}],"405gzo1m6uulua9":[{"n":"tree","t":"tree","i":["53-64"],"a":2,"b":3}],"405gzo1m6uuluaa":[{"n":"tree","t":"tree","i":["65-76"],"a":2,"b":3}],"405gzo1m6uuluab":[{"n":"tree","t":"tree","i":["77-96"],"a":3,"b":4}],"405gzo1m6uuluac":[{"n":"tree","t":"tree","i":["97-126"],"a":4,"b":5}],"405gzo1m6uuluae":[{"n":"tree","t":"tree","i":["127-156"],"a":4,"b":5}],"405gzo1m6uuluag":[{"n":"tree","t":"tree","i":["157-184"],"a":3,"b":6}],"405gzo1m6uuluah":[{"n":"tree","t":"tree","i":["185-232"],"a":5,"b":7}],"405gzo1m6uulubi":[{"n":"flower","t":"flowers","i":["102"],"a":0,"b":0}],"405gzo1m6uulubj":[{"n":"flower","t":"flowers","i":["103"],"a":0,"b":0}],"405gzo1m6uulubk":[{"n":"flower","t":"flowers","i":["104"],"a":0,"b":0}],"405gzo1m6uulubl":[{"n":"flower","t":"flowers","i":["105-106"],"a":0,"b":1}],"405gzo1m6uulubm":[{"n":"flower","t":"flowers","i":["107-108"],"a":0,"b":1}],"405gzo1m6uulubn":[{"n":"flower","t":"flowers","i":["109"],"a":0,"b":0}],"405gzo1m6uulubo":[{"n":"flower","t":"flowers","i":["110-111"],"a":0,"b":1}],"405gzo1m6uulubp":[{"n":"flower","t":"flowers","i":["112"],"a":0,"b":0}],"405gzo1m6uulubq":[{"n":"flower","t":"flowers","i":["113-114"],"a":0,"b":1}],"405gzo1m6uulubr":[{"n":"flower","t":"flowers","i":["115-116"],"a":0,"b":1}],"405gzo1m6uulubs":[{"n":"flower","t":"flowers","i":["117"],"a":0,"b":0}],"405gzo1m6uulubt":[{"n":"flower","t":"flowers","i":["118-119"],"a":0,"b":1}],"405gzo1m6uulubu":[{"n":"flower","t":"flowers","i":["120-121"],"a":0,"b":1}],"405gzo1m6uulubv":[{"n":"flower","t":"flowers","i":["122-123"],"a":0,"b":1}],"405gzo1m6uulubw":[{"n":"flower","t":"flowers","i":["124-125"],"a":0,"b":1}],"405gzo1m6uulubx":[{"n":"flower","t":"flowers","i":["126-127"],"a":0,"b":1}],"405gzo1m6uuluby":[{"n":"flower","t":"flowers","i":["128-129"],"a":0,"b":1}],"405gzo1m6uulubz":[{"n":"flower","t":"flowers","i":["130-131"],"a":0,"b":1}],"405gzo1m6uuluc0":[{"n":"flower","t":"flowers","i":["132-133"],"a":0,"b":1}],"405gzo1m6uuluc1":[{"n":"flower","t":"flowers","i":["134"],"a":0,"b":0}],"405gzo1m6uuluc2":[{"n":"flower","t":"flowers","i":["135"],"a":0,"b":0}],"405gzo1m6uuluc3":[{"n":"flower","t":"flowers","i":["136"],"a":0,"b":0}],"405gzo1m6uuluc4":[{"n":"flower","t":"flowers","i":["137"],"a":0,"b":0}],"405gzo1m6uuluc5":[{"n":"flower","t":"flowers","i":["138"],"a":0,"b":0}],"405gzo1m6uuluc6":[{"n":"flower","t":"flowers","i":["139"],"a":0,"b":0}],"405gzo1m6zd8c30":[{"n":"door","t":"door","i":["0-3"],"a":1,"b":1}],"405gzn1m70hzbpr":[{"n":"room layout","t":"room_layout","i":["0-399"],"a":24,"b":15,"z":0}],"405gzn1m70i5ogf":[{"n":"iso_door","t":"door","i":["4-9"],"a":1,"b":2}],"405gzn1m70qpgkf":[{"n":"bath","t":"bathroom","i":["0-29"],"a":5,"b":4}],"405gzn1m70qpgkh":[{"n":"carpet","t":"bathroom","i":["30-37"],"a":3,"b":1}],"405gzn1m70qpgki":[{"n":"window","t":"bathroom","i":["38-53"],"a":3,"b":3}],"405gzn1m70qpgkj":[{"n":"duck","t":"bathroom","i":["54"],"a":0,"b":0}],"405gzn1m70qpgkk":[{"n":"floor","t":"bathroom","i":["55-66"],"a":3,"b":2}],"405gzn1m70qpgkm":[{"n":"floor","t":"bathroom","i":["67-106"],"a":7,"b":4}],"405gzn1m70qpgkn":[{"n":"floor","t":"bathroom","i":["107-122"],"a":3,"b":3}],"405gzn1m70qpgkr":[{"n":"floor","t":"bathroom","i":["123-162"],"a":7,"b":4}],"405gzn1m70qpgks":[{"n":"hanger","t":"bathroom","i":["163-166"],"a":1,"b":1}],"405gzn1m70qpgkt":[{"n":"hanging towel","t":"bathroom","i":["167-174"],"a":1,"b":3}],"405gzn1m70qpgku":[{"n":"long shelf","t":"bathroom","i":["175-182"],"a":3,"b":1}],"405gzn1m70qpgkv":[{"n":"mirror","t":"bathroom","i":["183-194"],"a":2,"b":3}],"405gzn1m70qpgkw":[{"n":"bin","t":"bathroom","i":["195-198"],"a":1,"b":1}],"405gzn1m70qpgkx":[{"n":"shower floor","t":"bathroom","i":["199-214"],"a":3,"b":3}],"405gzn1m70qpgky":[{"n":"small shelf","t":"bathroom","i":["215-222"],"a":3,"b":1}],"405gzn1m70qpgkz":[{"n":"green soap","t":"bathroom","i":["223-226"],"a":1,"b":1}],"405gzn1m70qpgl0":[{"n":"red soap","t":"bathroom","i":["227-230"],"a":1,"b":1}],"405gzn1m70qpgl1":[{"n":"yellow soap","t":"bathroom","i":["231-234"],"a":1,"b":1}],"405gzn1m70qpgl2":[{"n":"shower tap","t":"bathroom","i":["235-250"],"a":3,"b":3}],"405gzn1m70qpgl3":[{"n":"wall tap","t":"bathroom","i":["251-254"],"a":1,"b":1}],"405gzn1m70qpgl4":[{"n":"tissues","t":"bathroom","i":["255-258"],"a":1,"b":1}],"405gzn1m70qpgl5":[{"n":"toilet paper","t":"bathroom","i":["259-262"],"a":1,"b":1}],"405gzn1m70qpgl6":[{"n":"blue towel","t":"bathroom","i":["263-266"],"a":1,"b":1}],"405gzn1m70qpgl7":[{"n":"green towel","t":"bathroom","i":["267-270"],"a":1,"b":1}],"405gzn1m70qpgl8":[{"n":"red towel","t":"bathroom","i":["271-274"],"a":1,"b":1}],"405gzn1m70qpgl9":[{"n":"bath wall","t":"bathroom","i":["275-314"],"a":4,"b":7}],"405gzn1m70qpgla":[{"n":"bath wall","t":"bathroom","i":["315-354"],"a":4,"b":7}],"405gzn1m70qpglb":[{"n":"bath wall","t":"bathroom","i":["355-366"],"a":2,"b":3}],"405gzn1m70qpglc":[{"n":"bath wall","t":"bathroom","i":["367-378"],"a":2,"b":3}],"405gzn1m70qpgld":[{"n":"bath wall","t":"bathroom","i":["379-390"],"a":2,"b":3}],"405gzn1m70qpgle":[{"n":"bath wall","t":"bathroom","i":["391-402"],"a":2,"b":3}],"405gzn1m70qpglf":[{"n":"toilet","t":"bathroom","i":["403-418"],"a":3,"b":3}],"405gzn1m70qpglg":[{"n":"toilet","t":"bathroom","i":["419-434"],"a":3,"b":3}],"405gzn1m70qpglh":[{"n":"bathroom furniture","t":"bathroom","i":["435-454"],"a":3,"b":4}],"405gzn1m70qpgli":[{"n":"sink","t":"bathroom","i":["455-474"],"a":3,"b":4}],"405gzn1m70qs9uc":[{"n":"bed","t":"bedroom","i":["0-34"],"a":6,"b":4}],"405gzn1m70qs9ud":[{"n":"bed","t":"bedroom","i":["35-74"],"a":7,"b":4}],"405gzn1m70qs9ue":[{"n":"bed","t":"bedroom","i":["75-109"],"a":6,"b":4}],"405gzn1m70qs9ug":[{"n":"bed","t":"bedroom","i":["110-157"],"a":7,"b":5}],"405gzn1m70qs9uh":[{"n":"night table","t":"bedroom","i":["158-173"],"a":3,"b":3}],"405gzn1m70qs9ui":[{"n":"pillow","t":"bedroom","i":["174-179"],"a":2,"b":1}],"405gzn1m70qthbn":[{"n":"carpet","t":"carpets","i":["0-31"],"a":7,"b":3}],"405gzn1m70qthbo":[{"n":"carpet","t":"carpets","i":["32-35"],"a":1,"b":1}],"405gzn1m70qthbp":[{"n":"carpet","t":"carpets","i":["36-59"],"a":5,"b":3}],"405gzn1m70qthbq":[{"n":"carpet","t":"carpets","i":["60-67"],"a":3,"b":1}],"405gzn1m70qu3kg":[{"n":"chair","t":"chairs","i":["0-11"],"a":2,"b":3}],"405gzn1m70qusd0":[{"n":"game console","t":"game_console","i":["0-11"],"a":3,"b":2}],"405gzn1m70qusd1":[{"n":"switch","t":"game_console","i":["12-20"],"a":2,"b":2}],"405gzn1m70qvlph":[{"n":"desk","t":"desk","i":["0-41"],"a":6,"b":5}],"405gzn1m70qvlpj":[{"n":"desk","t":"desk","i":["42-83"],"a":6,"b":5}],"405gzn1m70qw43g":[{"n":"door","t":"door","i":["10-41"],"a":3,"b":7}],"405gzn1m70qyqdf":[{"n":"floor","t":"floor","i":["0-11"],"a":3,"b":2}],"405gzn1m70qyqdg":[{"n":"floor","t":"floor","i":["12-23"],"a":3,"b":2}],"405gzn1m70qyqdh":[{"n":"floor","t":"floor","i":["24-35"],"a":3,"b":2}],"405gzn1m70qyqdi":[{"n":"floor","t":"floor","i":["36-47"],"a":3,"b":2}],"405gzn1m70qyqdj":[{"n":"floor","t":"floor","i":["48-59"],"a":3,"b":2}],"405gzn1m70qyqdk":[{"n":"floor","t":"floor","i":["60-71"],"a":3,"b":2}],"405gzn1m70qyqdl":[{"n":"floor","t":"floor","i":["72-83"],"a":3,"b":2}],"405gzn1m70qyqdm":[{"n":"floor","t":"floor","i":["84-95"],"a":3,"b":2}],"405gzn1m70qyqdn":[{"n":"floor","t":"floor","i":["96-107"],"a":3,"b":2}],"405gzn1m70qyqdo":[{"n":"floor","t":"floor","i":["108-119"],"a":3,"b":2}],"405gzn1m70qyqdp":[{"n":"floor","t":"floor","i":["120-131"],"a":3,"b":2}],"405gzn1m70qyqdq":[{"n":"floor","t":"floor","i":["132-143"],"a":3,"b":2}],"405gzn1m70qyqdr":[{"n":"floor","t":"floor","i":["144-155"],"a":3,"b":2}],"405gzn1m70qyqds":[{"n":"floor","t":"floor","i":["156-167"],"a":3,"b":2}],"405gzn1m70qyqdt":[{"n":"floor","t":"floor","i":["168-179"],"a":3,"b":2}],"405gzn1m70qyqdu":[{"n":"floor","t":"floor","i":["180-191"],"a":3,"b":2}],"405gzn1m70qyqdv":[{"n":"floor","t":"floor","i":["192-203"],"a":3,"b":2}],"405gzn1m70r132s":[{"n":"wall","t":"wall","i":["0-11"],"a":2,"b":3}],"405gzn1m70r132t":[{"n":"wall","t":"wall","i":["12-23"],"a":2,"b":3}],"405gzn1m70r132u":[{"n":"wall","t":"wall","i":["24-35"],"a":2,"b":3}],"405gzn1m70r132v":[{"n":"wall","t":"wall","i":["36-47"],"a":2,"b":3}],"405gzn1m70r132w":[{"n":"wall","t":"wall","i":["48-59"],"a":2,"b":3}],"405gzn1m70r132x":[{"n":"wall","t":"wall","i":["60-71"],"a":2,"b":3}],"405gzn1m70r132y":[{"n":"wall","t":"wall","i":["72-83"],"a":2,"b":3}],"405gzn1m70r132z":[{"n":"wall","t":"wall","i":["84-95"],"a":2,"b":3}],"405gzn1m70r1330":[{"n":"wall","t":"wall","i":["96-107"],"a":2,"b":3}],"405gzn1m70r1331":[{"n":"wall","t":"wall","i":["108-119"],"a":2,"b":3}],"405gzn1m70r1332":[{"n":"wall","t":"wall","i":["120-131"],"a":2,"b":3}],"405gzn1m70r1333":[{"n":"wall","t":"wall","i":["132-143"],"a":2,"b":3}],"405gzn1m70r1334":[{"n":"wall","t":"wall","i":["144-155"],"a":2,"b":3}],"405gzn1m70r1335":[{"n":"wall","t":"wall","i":["156-167"],"a":2,"b":3}],"405gzn1m70r1336":[{"n":"wall","t":"wall","i":["168-179"],"a":2,"b":3}],"405gzn1m70r1337":[{"n":"wall","t":"wall","i":["180-191"],"a":2,"b":3}],"405gzn1m70r1338":[{"n":"wall","t":"wall","i":["192-203"],"a":2,"b":3}],"405gzn1m70r1339":[{"n":"wall","t":"wall","i":["204-215"],"a":2,"b":3}],"405gzn1m70r1q37":[{"n":"fridge","t":"fridge","i":["0-27"],"a":3,"b":6}],"405gzn1m70r268y":[{"n":"gaming chair","t":"office","i":["0-15"],"a":3,"b":3}],"405gzn1m70r3mui":[{"n":"bottle","t":"kitchen","i":["0-3"],"a":1,"b":1}],"405gzn1m70r3muj":[{"n":"box","t":"kitchen","i":["4-7"],"a":1,"b":1}],"405gzn1m70r3muk":[{"n":"kettle","t":"kitchen","i":["8-11"],"a":1,"b":1}],"405gzn1m70r3mul":[{"n":"kitchen side","t":"kitchen","i":["12-31"],"a":3,"b":4}],"405gzn1m70r3mum":[{"n":"mug","t":"kitchen","i":["32-35"],"a":1,"b":1}],"405gzn1m70r3mun":[{"n":"oven","t":"kitchen","i":["36-55"],"a":3,"b":4}],"405gzn1m70r3muo":[{"n":"pot","t":"kitchen","i":["56-59"],"a":1,"b":1}],"405gzn1m70r41zt":[{"n":"lamp","t":"lighting","i":["18-21"],"a":1,"b":1}],"405gzn1m70r610f":[{"n":"air con","t":"living_room","i":["0-5"],"a":1,"b":2}],"405gzn1m70r610h":[{"n":"book","t":"living_room","i":["6-9"],"a":1,"b":1}],"405gzn1m70r610i":[{"n":"shelf","t":"living_room","i":["10-33"],"a":5,"b":3}],"405gzn1m70r610j":[{"n":"shelving","t":"living_room","i":["34-81"],"a":5,"b":7}],"405gzn1m70r610k":[{"n":"small table","t":"living_room","i":["82-105"],"a":5,"b":3}],"405gzn1m70r610l":[{"n":"speaker","t":"living_room","i":["106-121"],"a":3,"b":3}],"405gzn1m70r610m":[{"n":"table","t":"living_room","i":["122-157"],"a":5,"b":5}],"405gzn1m70r6f3a":[{"n":"microwave","t":"kitchen","i":["60-71"],"a":3,"b":2}],"405gzn1m70r9p8z":[{"n":"pc monitor","t":"office","i":["16-31"],"a":3,"b":3}],"405gzn1m70r9p90":[{"n":"old mac","t":"office","i":["32-47"],"a":3,"b":3}],"405gzn1m70r9p92":[{"n":"old mac","t":"office","i":["48-63"],"a":3,"b":3}],"405gzn1m70r9p94":[{"n":"old keyboard","t":"office","i":["64-67"],"a":1,"b":1}],"405gzn1m70r9p95":[{"n":"old pc","t":"office","i":["68-83"],"a":3,"b":3}],"405gzn1m70r9p96":[{"n":"old pc","t":"office","i":["84-99"],"a":3,"b":3}],"405gzn1m70r9p97":[{"n":"tower pc","t":"office","i":["100-107"],"a":1,"b":3}],"405gzn1m70r9p98":[{"n":"monitor","t":"office","i":["108-119"],"a":3,"b":2}],"405gzn1m70r9p99":[{"n":"monitor","t":"office","i":["120-135"],"a":3,"b":3}],"405gzn1m70r9p9a":[{"n":"monitor","t":"office","i":["136-143"],"a":1,"b":3}],"405gzn1m70r9p9b":[{"n":"tablet","t":"office","i":["144-147"],"a":1,"b":1}],"405gzn1m70r9p9t":[{"n":"gaming console","t":"game_console","i":["21-32"],"a":3,"b":2}],"405gzn1m70r9p9u":[{"n":"gaming console","t":"game_console","i":["33-44"],"a":3,"b":2}],"405gzn1m70r9p9v":[{"n":"mac","t":"game_console","i":["45-60"],"a":3,"b":3}],"405gzn1m70r9p9w":[{"n":"mac on","t":"game_console","i":["61-76"],"a":3,"b":3}],"405gzn1m70r9p9x":[{"n":"keyboard","t":"game_console","i":["77-85"],"a":2,"b":2}],"405gzn1m70ravvc":[{"n":"plants","t":"plants","i":["0-3"],"a":1,"b":1}],"405gzn1m70ravvd":[{"n":"plant","t":"plants","i":["4-7"],"a":1,"b":1}],"405gzn1m70ravve":[{"n":"plant","t":"plants","i":["8-11"],"a":1,"b":1}],"405gzn1m70ravvf":[{"n":"plant","t":"plants","i":["12-27"],"a":3,"b":3}],"405gzn1m70rbo2b":[{"n":"poster","t":"poster","i":["0-7"],"a":1,"b":3}],"405gzn1m70rbo2c":[{"n":"poster","t":"poster","i":["8-13"],"a":1,"b":2}],"405gzn1m70rcxqm":[{"n":"gift","t":"gift","i":["0-3"],"a":1,"b":1}],"405gzn1m70rcxqn":[{"n":"gift","t":"gift","i":["4-7"],"a":1,"b":1}],"405gzn1m70rcxqo":[{"n":"gift","t":"gift","i":["8-11"],"a":1,"b":1}],"405gzn1m70rcxqp":[{"n":"gift","t":"gift","i":["12-15"],"a":1,"b":1}],"405gzn1m70rcxqq":[{"n":"gift","t":"gift","i":["16-19"],"a":1,"b":1}],"405gzn1m70rcxqr":[{"n":"gift","t":"gift","i":["20-23"],"a":1,"b":1}],"405gzn1m70rcxqs":[{"n":"gift","t":"gift","i":["24-27"],"a":1,"b":1}],"405gzn1m70rcxqt":[{"n":"gift","t":"gift","i":["28-31"],"a":1,"b":1}],"405gzn1m70rcxqu":[{"n":"gift","t":"gift","i":["32-35"],"a":1,"b":1}],"405gzn1m70rcxqv":[{"n":"gift","t":"gift","i":["36-39"],"a":1,"b":1}],"405gzn1m70rcxqw":[{"n":"gift","t":"gift","i":["40-43"],"a":1,"b":1}],"405gzn1m70rdfpk":[{"n":"pillow","t":"living_room","i":["158-161"],"a":1,"b":1}],"405gzn1m70rdfpl":[{"n":"sofa","t":"living_room","i":["162-217"],"a":7,"b":6}],"405gzn1m70rfnh7":[{"n":"windows","t":"windows","i":["0-63"],"a":7,"b":7}],"405gzn1m70rfnha":[{"n":"windows","t":"windows","i":["64-127"],"a":7,"b":7}],"405gzn1m70rfnhc":[{"n":"windows","t":"windows","i":["128-191"],"a":7,"b":7}],"405gzn1m70rfnhd":[{"n":"windows","t":"windows","i":["192-233"],"a":6,"b":5}],"405gzn1m70rfnhf":[{"n":"windows","t":"windows","i":["234-275"],"a":5,"b":6}],"405gzn1m70rfnhh":[{"n":"windows","t":"windows","i":["276-317"],"a":5,"b":6}],"405gzn1m70rfnhi":[{"n":"windows","t":"windows","i":["318-337"],"a":3,"b":4}],"405gzn1m70rfnhj":[{"n":"windows","t":"windows","i":["338-379"],"a":6,"b":5}],"405gzn1m70rfnhk":[{"n":"windows","t":"windows","i":["380-409"],"a":5,"b":4}],"405gzm1m73890nx":[{"n":"table","t":"test","i":["0-3"],"a":1,"b":1}],"405gzm1m73890ny":[{"n":"cube","t":"test","i":["4-12"],"a":2,"b":2}],"405gzm1m7389njw":[{"n":"bed","t":"test","i":["13-21"],"a":2,"b":2}],"405gzm1m7389njy":[{"n":"bed","t":"test","i":["22-30"],"a":2,"b":2}],"405gzm1m7389njz":[{"n":"tile","t":"test","i":["31-34"],"a":1,"b":1}],"405gzm1m7389nk1":[{"n":"cube_tile","t":"test","i":["35-46"],"a":3,"b":2}],"405gzo1m7ifvue6":[{"n":"package","t":"packages","i":["0-3"],"a":1,"b":1}],"405gzo1m7ifvue7":[{"n":"package","t":"packages","i":["4-7"],"a":1,"b":1}],"405gzo1m7ifvue8":[{"n":"package","t":"packages","i":["8-11"],"a":1,"b":1}],"405gzo1m7ifvue9":[{"n":"package","t":"packages","i":["12-15"],"a":1,"b":1}],"405gzo1m7ifvuea":[{"n":"package","t":"packages","i":["16-19"],"a":1,"b":1}],"405gzo1m7ifvueb":[{"n":"package","t":"packages","i":["20-23"],"a":1,"b":1}],"405gzo1m7ifvuec":[{"n":"package","t":"packages","i":["24-27"],"a":1,"b":1}],"405gzo1m7ifvued":[{"n":"package","t":"packages","i":["28-31"],"a":1,"b":1}],"405gzo1m7ifvuee":[{"n":"package","t":"packages","i":["32-35"],"a":1,"b":1}],"405gzo1m7ifvuef":[{"n":"package","t":"packages","i":["36-39"],"a":1,"b":1}],"405gzo1m7ifvueg":[{"n":"package","t":"packages","i":["40-43"],"a":1,"b":1}],"405gzo1m7ifvueh":[{"n":"package","t":"packages","i":["44-47"],"a":1,"b":1}],"405gzo1m7ifvuei":[{"n":"package","t":"packages","i":["48-56"],"a":2,"b":2}],"405gzo1m7ifvuej":[{"n":"package","t":"packages","i":["57-68"],"a":3,"b":2}],"405gzo1m7ifvuek":[{"n":"package","t":"packages","i":["69-80"],"a":2,"b":3}],"405gzo1m7ifvuel":[{"n":"package","t":"packages","i":["81-92"],"a":2,"b":3}],"405gzo1m7ifvuem":[{"n":"package","t":"packages","i":["93-104"],"a":2,"b":3}],"405gzo1m7ifvuen":[{"n":"package","t":"packages","i":["105-113"],"a":2,"b":2}],"405gzo1m7ifvufv":[{"n":"tree","t":"tree","i":["233-244"],"a":2,"b":3}],"405gzo1m7ifvufw":[{"n":"tree","t":"tree","i":["245-256"],"a":2,"b":3}],"405gzo1m7ifvufx":[{"n":"tree","t":"tree","i":["257-268"],"a":2,"b":3}],"405gzo1m7ifvufy":[{"n":"tree","t":"tree","i":["269-280"],"a":2,"b":3}],"405gzo1m7ifvufz":[{"n":"tree","t":"tree","i":["281-286"],"a":1,"b":2}],"405gzo1m7ifvug0":[{"n":"tree","t":"tree","i":["287-292"],"a":1,"b":2}],"405gzo1m7ifvug1":[{"n":"tree","t":"tree","i":["293-298"],"a":1,"b":2}],"405gzo1m7ifvug7":[{"n":"tree","t":"tree","i":["299-304"],"a":1,"b":2}],"405gzo1m7ifvug8":[{"n":"tree","t":"tree","i":["305-310"],"a":1,"b":2}],"405gzo1m7ifvug9":[{"n":"tree","t":"tree","i":["311-322"],"a":2,"b":3}],"405gzo1m7ifvuga":[{"n":"tree","t":"tree","i":["323-334"],"a":2,"b":3}],"405gzo1m7ifvugb":[{"n":"tree","t":"tree","i":["335-346"],"a":2,"b":3}],"405gzo1m7ifvugc":[{"n":"tree","t":"tree","i":["347-352"],"a":1,"b":2}],"405gzo1m7ifvugd":[{"n":"tree","t":"tree","i":["353-358"],"a":1,"b":2}],"405gzo1m7ifvuge":[{"n":"tree","t":"tree","i":["359-364"],"a":1,"b":2}],"405gzo1m7ifvugf":[{"n":"tree","t":"tree","i":["365-370"],"a":1,"b":2}],"405gzo1m7ifvugg":[{"n":"tree","t":"tree","i":["371-382"],"a":2,"b":3}],"405gzo1m7ifvugh":[{"n":"tree","t":"tree","i":["383-394"],"a":2,"b":3}],"405gzo1m7ifvugi":[{"n":"tree","t":"tree","i":["395-406"],"a":2,"b":3}],"405gzo1m7ifvugj":[{"n":"tree","t":"tree","i":["407-412"],"a":1,"b":2}],"405gzo1m7ifvugk":[{"n":"tree","t":"tree","i":["413-418"],"a":1,"b":2}],"405gzo1m7ifvugl":[{"n":"tree","t":"tree","i":["419-424"],"a":1,"b":2}],"405gzo1m7ifvugm":[{"n":"tree","t":"tree","i":["425-430"],"a":1,"b":2}],"405gzo1m7ifvugn":[{"n":"tree","t":"tree","i":["431-442"],"a":2,"b":3}],"405gzo1m7ifvugs":[{"n":"tree","t":"tree","i":["443-454"],"a":2,"b":3}],"405gzo1m7ifvugt":[{"n":"tree","t":"tree","i":["455-466"],"a":2,"b":3}],"405gzo1m7ifvugu":[{"n":"tree","t":"tree","i":["467-478"],"a":2,"b":3}],"405gzo1m7ifvugv":[{"n":"tree","t":"tree","i":["479-490"],"a":2,"b":3}],"405gzo1m7ifvugw":[{"n":"tree","t":"tree","i":["491-502"],"a":2,"b":3}],"405gzo1m7ifvugx":[{"n":"tree","t":"tree","i":["503-514"],"a":2,"b":3}],"405gzo1m7ifvugy":[{"n":"tree","t":"tree","i":["515-526"],"a":2,"b":3}],"405gzo1m7ifvugz":[{"n":"tree","t":"tree","i":["527-538"],"a":2,"b":3}],"405gzo1m7ifvuh0":[{"n":"tree","t":"tree","i":["539-550"],"a":2,"b":3}],"405gzo1m7ifvuh1":[{"n":"tree","t":"tree","i":["551-562"],"a":2,"b":3}],"405gzo1m7ifvuh2":[{"n":"tree","t":"tree","i":["563-574"],"a":2,"b":3}],"405gzo1m7ifvuh3":[{"n":"tree","t":"tree","i":["575-586"],"a":2,"b":3}],"405gzo1m7ifvuh4":[{"n":"tree","t":"tree","i":["587-598"],"a":2,"b":3}],"405gzo1m7ifvuh7":[{"n":"tree","t":"tree","i":["599-610"],"a":2,"b":3}],"405gzo1m7ifvuh8":[{"n":"tree","t":"tree","i":["611-622"],"a":2,"b":3}],"405gzo1m7ifvuh9":[{"n":"tree","t":"tree","i":["623-637"],"a":2,"b":4}],"405gzo1m7ifvuha":[{"n":"tree","t":"tree","i":["638-652"],"a":2,"b":4}],"405gzo1m7ifvuhb":[{"n":"tree","t":"tree","i":["653-667"],"a":2,"b":4}],"405gzo1m7ifvuhc":[{"n":"tree","t":"tree","i":["668-682"],"a":2,"b":4}],"405gzo1m7ifvuhd":[{"n":"tree","t":"tree","i":["683-697"],"a":2,"b":4}],"405gzo1m7ifvuhe":[{"n":"tree","t":"tree","i":["698-712"],"a":2,"b":4}],"405gzo1m7ifvuhf":[{"n":"tree","t":"tree","i":["713-727"],"a":2,"b":4}],"405gzo1m7ifvuhg":[{"n":"tree","t":"tree","i":["728-742"],"a":2,"b":4}],"405gzo1m7ifvuhh":[{"n":"tree","t":"tree","i":["743-757"],"a":2,"b":4}],"405gzo1m7ifvuhi":[{"n":"tree","t":"tree","i":["758-772"],"a":2,"b":4}],"405gzo1m7ifvuhj":[{"n":"tree","t":"tree","i":["773-787"],"a":2,"b":4}],"405gzo1m7ifvuhk":[{"n":"tree","t":"tree","i":["788-802"],"a":2,"b":4}],"405gzo1m7ifvuhl":[{"n":"tree","t":"tree","i":["803-817"],"a":2,"b":4}],"405gzo1m7ifvuhm":[{"n":"tree","t":"tree","i":["818-832"],"a":2,"b":4}],"405gzo1m7ifvuhn":[{"n":"tree","t":"tree","i":["833-847"],"a":2,"b":4}],"405gzo1m7ifvuho":[{"n":"tree","t":"tree","i":["848-862"],"a":2,"b":4}],"405gzo1m7ifvuhp":[{"n":"tree","t":"tree","i":["863-883"],"a":2,"b":6}],"405gzo1m7ifvuhq":[{"n":"tree","t":"tree","i":["884-904"],"a":2,"b":6}],"405gzo1m7ifvuhr":[{"n":"tree","t":"tree","i":["905-925"],"a":2,"b":6}],"405gzo1m7ifvuhs":[{"n":"tree","t":"tree","i":["926-946"],"a":2,"b":6}],"405gzo1m7ifvuht":[{"n":"tree","t":"tree","i":["947-967"],"a":2,"b":6}],"405gzo1m7ifvuhu":[{"n":"tree","t":"tree","i":["968-988"],"a":2,"b":6}],"405gzo1m7ifvuhv":[{"n":"tree","t":"tree","i":["989-1009"],"a":2,"b":6}],"405gzo1m7ifvuhw":[{"n":"tree","t":"tree","i":["1010-1030"],"a":2,"b":6}],"405gzo1m7ifvuhx":[{"n":"tree","t":"tree","i":["1031-1051"],"a":2,"b":6}],"405gzo1m7ifvuhy":[{"n":"tree","t":"tree","i":["1052-1072"],"a":2,"b":6}],"405gzo1m7ifvuhz":[{"n":"tree","t":"tree","i":["1073-1093"],"a":2,"b":6}],"405gzo1m7ifvui0":[{"n":"tree","t":"tree","i":["1094-1114"],"a":2,"b":6}],"405gzo1m7ifvui1":[{"n":"tree","t":"tree","i":["1115-1135"],"a":2,"b":6}],"405gzo1m7ifvui2":[{"n":"tree","t":"tree","i":["1136-1156"],"a":2,"b":6}],"405gzo1m7ifvui3":[{"n":"tree","t":"tree","i":["1157-1177"],"a":2,"b":6}],"405gzo1m7ifvui4":[{"n":"tree","t":"tree","i":["1178-1198"],"a":2,"b":6}],"405gzo1m7ig23eh":[{"n":"window","t":"windows","i":["410-415"],"a":1,"b":2}],"405gzo1m7ig23ei":[{"n":"window","t":"windows","i":["416-421"],"a":1,"b":2}],"405gzo1m7ig23ej":[{"n":"window","t":"windows","i":["422-427"],"a":1,"b":2}],"405gzo1m7ig23ek":[{"n":"window","t":"windows","i":["428-439"],"a":3,"b":2}],"405gzo1m7ig23el":[{"n":"window","t":"windows","i":["440-445"],"a":1,"b":2}],"405gzo1m7ig23em":[{"n":"window","t":"windows","i":["446-451"],"a":1,"b":2}],"405gzo1m7ig23en":[{"n":"window","t":"windows","i":["452-457"],"a":1,"b":2}],"405gzo1m7ig23eo":[{"n":"window","t":"windows","i":["458-469"],"a":3,"b":2}],"405gzo1m7ig23ep":[{"n":"window","t":"windows","i":["470-475"],"a":1,"b":2}],"405gzo1m7ig23er":[{"n":"window","t":"windows","i":["476-481"],"a":1,"b":2}],"405gzo1m7ig23es":[{"n":"window","t":"windows","i":["482-487"],"a":1,"b":2}],"405gzo1m7ig23et":[{"n":"window","t":"windows","i":["488-499"],"a":3,"b":2}],"405gzo1m7ig23eu":[{"n":"window","t":"windows","i":["500-505"],"a":1,"b":2}],"405gzo1m7ig23ev":[{"n":"window","t":"windows","i":["506-511"],"a":1,"b":2}],"405gzo1m7ig23ew":[{"n":"window","t":"windows","i":["512-517"],"a":1,"b":2}],"405gzo1m7ig23ex":[{"n":"window","t":"windows","i":["518-529"],"a":3,"b":2}],"405gzo1m7ig23ey":[{"n":"window","t":"windows","i":["530-535"],"a":1,"b":2}],"405gzo1m7ig23ez":[{"n":"window","t":"windows","i":["536-541"],"a":1,"b":2}],"405gzo1m7ig23f0":[{"n":"window","t":"windows","i":["542-547"],"a":1,"b":2}],"405gzo1m7ig23f1":[{"n":"window","t":"windows","i":["548-559"],"a":3,"b":2}],"405gzo1m7ig23f2":[{"n":"window","t":"windows","i":["560-565"],"a":1,"b":2}],"405gzo1m7ig23f3":[{"n":"window","t":"windows","i":["566-571"],"a":1,"b":2}],"405gzo1m7ig23f4":[{"n":"window","t":"windows","i":["572-577"],"a":1,"b":2}],"405gzo1m7ig23f5":[{"n":"window","t":"windows","i":["578-589"],"a":3,"b":2}],"405gzo1m7ig23f6":[{"n":"window","t":"windows","i":["590-595"],"a":1,"b":2}],"405gzo1m7ig23f7":[{"n":"window","t":"windows","i":["596-601"],"a":1,"b":2}],"405gzo1m7ig23f8":[{"n":"window","t":"windows","i":["602-607"],"a":1,"b":2}],"405gzo1m7ig23f9":[{"n":"window","t":"windows","i":["608-619"],"a":3,"b":2}],"405gzo1m7ig23fa":[{"n":"window","t":"windows","i":["620-625"],"a":1,"b":2}],"405gzo1m7ig23fb":[{"n":"window","t":"windows","i":["626-631"],"a":1,"b":2}],"405gzo1m7ig23fc":[{"n":"window","t":"windows","i":["632-637"],"a":1,"b":2}],"405gzo1m7ig23fd":[{"n":"window","t":"windows","i":["638-649"],"a":3,"b":2}],"405gzo1m7ig23fe":[{"n":"window","t":"windows","i":["650-655"],"a":1,"b":2}],"405gzo1m7ig23ff":[{"n":"window","t":"windows","i":["656-661"],"a":1,"b":2}],"405gzo1m7ig23fg":[{"n":"window","t":"windows","i":["662-667"],"a":1,"b":2}],"405gzo1m7ig23fh":[{"n":"window","t":"windows","i":["668-679"],"a":3,"b":2}],"405gzo1m7ig23fi":[{"n":"window","t":"windows","i":["680-685"],"a":1,"b":2}],"405gzo1m7ig23fj":[{"n":"window","t":"windows","i":["686-691"],"a":1,"b":2}],"405gzo1m7ig23fk":[{"n":"window","t":"windows","i":["692-697"],"a":1,"b":2}],"405gzo1m7ig23fl":[{"n":"window","t":"windows","i":["698-709"],"a":3,"b":2}],"405gzo1m7ig23fm":[{"n":"window","t":"windows","i":["710-721"],"a":3,"b":2}],"405gzo1m7ig23fn":[{"n":"window","t":"windows","i":["722-733"],"a":3,"b":2}],"405gzo1m7ig23fo":[{"n":"window","t":"windows","i":["734-745"],"a":3,"b":2}],"405gzo1m7ig23fp":[{"n":"window","t":"windows","i":["746-757"],"a":3,"b":2}],"405gzo1m7ig23fq":[{"n":"window","t":"windows","i":["758-769"],"a":3,"b":2}],"405gzo1m7ig23fr":[{"n":"window","t":"windows","i":["770-781"],"a":3,"b":2}],"405gzo1m7ig23fs":[{"n":"window","t":"windows","i":["782-793"],"a":3,"b":2}],"405gzo1m7ig23ft":[{"n":"window","t":"windows","i":["794-805"],"a":3,"b":2}],"405gzo1m7ig23fu":[{"n":"window","t":"windows","i":["806-817"],"a":3,"b":2}],"405gzo1m7ig23fv":[{"n":"window","t":"windows","i":["818-829"],"a":3,"b":2}],"405gzo1m7ig23fw":[{"n":"window","t":"windows","i":["830-841"],"a":3,"b":2}],"405gzo1m7ig23fx":[{"n":"window","t":"windows","i":["842-853"],"a":3,"b":2}],"405gzo1m7ig23fy":[{"n":"window","t":"windows","i":["854-859"],"a":1,"b":2}],"405gzo1m7ig23fz":[{"n":"window","t":"windows","i":["860-865"],"a":1,"b":2}],"405gzo1m7ig23g0":[{"n":"window","t":"windows","i":["866-871"],"a":1,"b":2}],"405gzo1m7ig23g1":[{"n":"window","t":"windows","i":["872-877"],"a":1,"b":2}],"405gzo1m7ig23g2":[{"n":"window","t":"windows","i":["878-880"],"a":0,"b":2}],"405gzo1m7ig23g3":[{"n":"window","t":"windows","i":["881-883"],"a":0,"b":2}],"405gzo1m7ig23g4":[{"n":"window","t":"windows","i":["884-886"],"a":0,"b":2}],"405gzo1m7ig23g5":[{"n":"window","t":"windows","i":["887-892"],"a":1,"b":2}],"405gzo1m7ig23g6":[{"n":"window","t":"windows","i":["893-898"],"a":1,"b":2}],"405gzo1m7ig23g7":[{"n":"window","t":"windows","i":["899-901"],"a":0,"b":2}],"405gzo1m7ig23g8":[{"n":"window","t":"windows","i":["902-904"],"a":0,"b":2}],"405gzo1m7ig23g9":[{"n":"window","t":"windows","i":["905-907"],"a":0,"b":2}],"405gzo1m7ig23ga":[{"n":"window","t":"windows","i":["908-913"],"a":1,"b":2}],"405gzo1m7ig23gb":[{"n":"window","t":"windows","i":["914-919"],"a":1,"b":2}],"405gzo1m7ig3zon":[{"n":"door","t":"door","i":["42-50"],"a":2,"b":2}],"405gzo1m7ig3zoo":[{"n":"door","t":"door","i":["51-59"],"a":2,"b":2}],"405gzo1m7ig3zop":[{"n":"door","t":"door","i":["60-68"],"a":2,"b":2}],"405gzo1m7ig3zoq":[{"n":"door","t":"door","i":["69-77"],"a":2,"b":2}],"405gzo1m7ig3zor":[{"n":"door","t":"door","i":["78-83"],"a":2,"b":1}],"405gzo1m7ig3zos":[{"n":"door","t":"door","i":["84-89"],"a":2,"b":1}],"405gzo1m7ig3zot":[{"n":"door","t":"door","i":["90-98"],"a":2,"b":2}],"405gzo1m7ig3zou":[{"n":"door","t":"door","i":["99-107"],"a":2,"b":2}],"405gzo1m7ig3zov":[{"n":"door","t":"door","i":["108-116"],"a":2,"b":2}],"405gzo1m7ig3zow":[{"n":"door","t":"door","i":["117-128"],"a":2,"b":3}],"405gzo1m7ig3zox":[{"n":"door","t":"door","i":["129-140"],"a":2,"b":3}],"405gzo1m7ig3zoy":[{"n":"door","t":"door","i":["141-146"],"a":2,"b":1}],"405gzo1m7ig3zoz":[{"n":"door","t":"door","i":["147-152"],"a":2,"b":1}],"405gzo1m7ig3zp0":[{"n":"door","t":"door","i":["153-158"],"a":1,"b":2}],"405gzo1m7ig3zp1":[{"n":"door","t":"door","i":["159-162"],"a":1,"b":1}],"405gzo1m7ig3zp2":[{"n":"door","t":"door","i":["163-166"],"a":1,"b":1}],"405gzo1m7ig3zp3":[{"n":"door","t":"door","i":["167-172"],"a":1,"b":2}],"405gzo1m7ig3zp4":[{"n":"door","t":"door","i":["173-178"],"a":1,"b":2}],"405gzo1m7ig3zp5":[{"n":"door","t":"door","i":["179-187"],"a":2,"b":2}],"405gzo1m7ig5sew":[{"n":"stump","t":"tree","i":["1199-1204"],"a":1,"b":2}],"405gzo1m7ig5sex":[{"n":"stump","t":"tree","i":["1205-1210"],"a":1,"b":2}],"405gzo1m7ig5sey":[{"n":"stump","t":"tree","i":["1211-1216"],"a":1,"b":2}],"405gzo1m7ig5sez":[{"n":"stump","t":"tree","i":["1217-1222"],"a":1,"b":2}],"405gzo1m7ig5sf0":[{"n":"stump","t":"tree","i":["1223-1228"],"a":1,"b":2}],"405gzo1m7ig5sf1":[{"n":"stump","t":"tree","i":["1229-1232"],"a":1,"b":1}],"405gzo1m7ig5sf2":[{"n":"stump","t":"tree","i":["1233-1236"],"a":1,"b":1}],"405gzo1m7ig5sf3":[{"n":"stump","t":"tree","i":["1237-1240"],"a":1,"b":1}],"405gzo1m7ig5sf4":[{"n":"stump","t":"tree","i":["1241-1244"],"a":1,"b":1}],"405gzo1m7ig5sf5":[{"n":"stump","t":"tree","i":["1245-1248"],"a":1,"b":1}],"405gzo1m7ig5sf6":[{"n":"stump","t":"tree","i":["1249-1250"],"a":1,"b":0}],"405gzo1m7ig5sf7":[{"n":"stump","t":"tree","i":["1251-1252"],"a":1,"b":0}],"405gzo1m7ig5sf8":[{"n":"stump","t":"tree","i":["1253-1254"],"a":1,"b":0}],"405gzo1m7ig5sf9":[{"n":"stump","t":"tree","i":["1255-1256"],"a":1,"b":0}],"405gzo1m7ig5sfa":[{"n":"stump","t":"tree","i":["1257-1260"],"a":1,"b":1}],"405gzo1m7ig722g":[{"n":"barrel","t":"barrels","i":["0-3"],"a":1,"b":1}],"405gzo1m7ig722h":[{"n":"barrel","t":"barrels","i":["4-7"],"a":1,"b":1}],"405gzo1m7ig722j":[{"n":"barrel","t":"barrels","i":["8-11"],"a":1,"b":1}],"405gzo1m7ig722k":[{"n":"barrel","t":"barrels","i":["12-15"],"a":1,"b":1}],"405gzo1m7ig722l":[{"n":"barrel","t":"barrels","i":["16-19"],"a":1,"b":1}],"405gzo1m7ig722m":[{"n":"barrel","t":"barrels","i":["20-23"],"a":1,"b":1}],"405gzo1m7ig722n":[{"n":"barrel","t":"barrels","i":["24-27"],"a":1,"b":1}],"405gzo1m7ig722o":[{"n":"barrel","t":"barrels","i":["28-31"],"a":1,"b":1}],"405gzo1m7ig722p":[{"n":"barrel","t":"barrels","i":["32-35"],"a":1,"b":1}],"405gzo1m7ig722q":[{"n":"barrel","t":"barrels","i":["36-39"],"a":1,"b":1}],"405gzo1m7ig8k4a":[{"n":"rock","t":"rock","i":["0-1"],"a":0,"b":1}],"405gzo1m7ig8k4b":[{"n":"rock","t":"rock","i":["2-3"],"a":1,"b":0}],"405gzo1m7ig8k4c":[{"n":"rock","t":"rock","i":["4"],"a":0,"b":0}],"405gzo1m7ig8k4d":[{"n":"rock","t":"rock","i":["5"],"a":0,"b":0}],"405gzo1m7ig8k4e":[{"n":"rock","t":"rock","i":["6-7"],"a":1,"b":0}],"405gzo1m7ig8k4f":[{"n":"rock","t":"rock","i":["8-11"],"a":1,"b":1}],"405gzo1m7ig8k4g":[{"n":"rock","t":"rock","i":["12-13"],"a":1,"b":0}],"405gzo1m7ig8k4h":[{"n":"rock","t":"rock","i":["14-15"],"a":0,"b":1}],"405gzo1m7ig8k4i":[{"n":"rock","t":"rock","i":["16-17"],"a":1,"b":0}],"405gzo1m7ig8k4j":[{"n":"rock","t":"rock","i":["18"],"a":0,"b":0}],"405gzo1m7ig8k4k":[{"n":"rock","t":"rock","i":["19-22"],"a":1,"b":1}],"405gzo1m7ig8k4l":[{"n":"rock","t":"rock","i":["23"],"a":0,"b":0}],"405gzo1m7ig8k4m":[{"n":"rock","t":"rock","i":["24-25"],"a":1,"b":0}],"405gzo1m7ig8k4n":[{"n":"rock","t":"rock","i":["26-27"],"a":0,"b":1}],"405gzo1m7ig8k4o":[{"n":"rock","t":"rock","i":["28-29"],"a":1,"b":0}],"405gzo1m7ig8k4p":[{"n":"rock","t":"rock","i":["30"],"a":0,"b":0}],"405gzo1m7ig8k4q":[{"n":"rock","t":"rock","i":["31-34"],"a":1,"b":1}],"405gzo1m7ig8k4r":[{"n":"rock","t":"rock","i":["35"],"a":0,"b":0}],"405gzo1m7ig8k4s":[{"n":"rock","t":"rock","i":["36-37"],"a":1,"b":0}],"405gzo1m7igag0n":[{"n":"plant","t":"plants","i":["28"],"a":0,"b":0}],"405gzo1m7igag0o":[{"n":"plant","t":"plants","i":["29"],"a":0,"b":0}],"405gzo1m7igag0p":[{"n":"plant","t":"plants","i":["30"],"a":0,"b":0}],"405gzo1m7igag0q":[{"n":"plant","t":"plants","i":["31-32"],"a":0,"b":1}],"405gzo1m7igag0r":[{"n":"plant","t":"plants","i":["33"],"a":0,"b":0}],"405gzo1m7igag0s":[{"n":"plant","t":"plants","i":["34"],"a":0,"b":0}],"405gzo1m7igag0t":[{"n":"plant","t":"plants","i":["35"],"a":0,"b":0}],"405gzo1m7igag0u":[{"n":"plant","t":"plants","i":["36"],"a":0,"b":0}],"405gzo1m7igag0v":[{"n":"plant","t":"plants","i":["37"],"a":0,"b":0}],"405gzo1m7igag0w":[{"n":"plant","t":"plants","i":["38"],"a":0,"b":0}],"405gzo1m7igag0x":[{"n":"plant","t":"plants","i":["39"],"a":0,"b":0}],"405gzo1m7igag0y":[{"n":"plant","t":"plants","i":["40"],"a":0,"b":0}],"405gzo1m7igag0z":[{"n":"plant","t":"plants","i":["41"],"a":0,"b":0}],"405gzo1m7igag10":[{"n":"plant","t":"plants","i":["42"],"a":0,"b":0}],"405gzo1m7igag11":[{"n":"plant","t":"plants","i":["43-44"],"a":0,"b":1}],"405gzo1m7igag12":[{"n":"plant","t":"plants","i":["45"],"a":0,"b":0}],"405gzo1m7igag13":[{"n":"plant","t":"plants","i":["46"],"a":0,"b":0}],"405gzo1m7igag14":[{"n":"plant","t":"plants","i":["47"],"a":0,"b":0}],"405gzo1m7igag15":[{"n":"plant","t":"plants","i":["48"],"a":0,"b":0}],"405gzo1m7igag16":[{"n":"plant","t":"plants","i":["49"],"a":0,"b":0}],"405gzo1m7igag17":[{"n":"plant","t":"plants","i":["50"],"a":0,"b":0}],"405gzo1m7igag18":[{"n":"plant","t":"plants","i":["51"],"a":0,"b":0}],"405gzo1m7igag19":[{"n":"plant","t":"plants","i":["52"],"a":0,"b":0}],"405gzo1m7igag1a":[{"n":"plant","t":"plants","i":["53"],"a":0,"b":0}],"405gzo1m7igag1b":[{"n":"plant","t":"plants","i":["54"],"a":0,"b":0}],"405gzo1m7igag1c":[{"n":"plant","t":"plants","i":["55"],"a":0,"b":0}],"405gzo1m7igag1d":[{"n":"plant","t":"plants","i":["56-57"],"a":0,"b":1}],"405gzo1m7igag1e":[{"n":"plant","t":"plants","i":["58-59"],"a":0,"b":1}],"405gzo1m7igag1f":[{"n":"plant","t":"plants","i":["60"],"a":0,"b":0}],"405gzo1m7igag1g":[{"n":"plant","t":"plants","i":["61-62"],"a":0,"b":1}],"405gzo1m7igag1h":[{"n":"plant","t":"plants","i":["63-64"],"a":0,"b":1}],"405gzo1m7igag1i":[{"n":"plant","t":"plants","i":["65-66"],"a":0,"b":1}],"405gzo1m7igag1j":[{"n":"plant","t":"plants","i":["67-68"],"a":0,"b":1}],"405gzo1m7igdjir":[{"n":"plant","t":"plants","i":["69"],"a":0,"b":0}],"405gzo1m7igdjis":[{"n":"plant","t":"plants","i":["70"],"a":0,"b":0}],"405gzo1m7igdjit":[{"n":"plant","t":"plants","i":["71"],"a":0,"b":0}],"405gzo1m7igdjiu":[{"n":"plant","t":"plants","i":["72"],"a":0,"b":0}],"405gzo1m7igdjiv":[{"n":"plant","t":"plants","i":["73"],"a":0,"b":0}],"405gzo1m7igdjiw":[{"n":"plant","t":"plants","i":["74"],"a":0,"b":0}],"405gzo1m7igdjix":[{"n":"plant","t":"plants","i":["75-76"],"a":0,"b":1}],"405gzo1m7igdjiy":[{"n":"plant","t":"plants","i":["77-78"],"a":0,"b":1}],"405gzo1m7igdjiz":[{"n":"plant","t":"plants","i":["79-80"],"a":0,"b":1}],"405gzo1m7igdjj0":[{"n":"plant","t":"plants","i":["81-82"],"a":0,"b":1}],"405gzo1m7igdjj1":[{"n":"plant","t":"plants","i":["83"],"a":0,"b":0}],"405gzo1m7igdjj2":[{"n":"plant","t":"plants","i":["84"],"a":0,"b":0}],"405gzo1m7igdjj3":[{"n":"plant","t":"plants","i":["85"],"a":0,"b":0}],"405gzo1m7igdjj4":[{"n":"plant","t":"plants","i":["86"],"a":0,"b":0}],"405gzo1m7igdjj5":[{"n":"plant","t":"plants","i":["87"],"a":0,"b":0}],"405gzo1m7igdjj6":[{"n":"plant","t":"plants","i":["88"],"a":0,"b":0}],"405gzo1m7igdjj7":[{"n":"plant","t":"plants","i":["89-90"],"a":0,"b":1}],"405gzo1m7igdjj8":[{"n":"plant","t":"plants","i":["91-92"],"a":0,"b":1}],"405gzo1m7igdjj9":[{"n":"plant","t":"plants","i":["93-94"],"a":0,"b":1}],"405gzo1m7igdjja":[{"n":"plant","t":"plants","i":["95-96"],"a":0,"b":1}],"405gzo1m7igdjjb":[{"n":"plant","t":"plants","i":["97"],"a":0,"b":0}],"405gzo1m7igdjjc":[{"n":"plant","t":"plants","i":["98"],"a":0,"b":0}],"405gzo1m7igdjjd":[{"n":"plant","t":"plants","i":["99"],"a":0,"b":0}],"405gzo1m7igdjje":[{"n":"plant","t":"plants","i":["100-101"],"a":0,"b":1}],"405gzo1m7igdjjf":[{"n":"plant","t":"plants","i":["102-103"],"a":0,"b":1}],"405gzo1m7igdjjg":[{"n":"plant","t":"plants","i":["104-105"],"a":0,"b":1}],"405gzo1m7igdjjh":[{"n":"plant","t":"plants","i":["106-107"],"a":0,"b":1}],"405gzo1m7igdjji":[{"n":"plant","t":"plants","i":["108"],"a":0,"b":0}],"405gzo1m7igdjjj":[{"n":"plant","t":"plants","i":["109"],"a":0,"b":0}],"405gzo1m7igdjjk":[{"n":"plant","t":"plants","i":["110"],"a":0,"b":0}],"405gzo1m7igdjjl":[{"n":"plant","t":"plants","i":["111-112"],"a":0,"b":1}],"405gzo1m7igdjjm":[{"n":"plant","t":"plants","i":["113-114"],"a":0,"b":1}],"405gzo1m7igdjjn":[{"n":"plant","t":"plants","i":["115-116"],"a":0,"b":1}],"405gzo1m7igdjjo":[{"n":"plant","t":"plants","i":["117-118"],"a":0,"b":1}],"405gzo1m7igdjjp":[{"n":"plant","t":"plants","i":["119-120"],"a":0,"b":1}],"405gzo1m7igdjjq":[{"n":"plant","t":"plants","i":["121-122"],"a":0,"b":1}],"405gzo1m7igdjjr":[{"n":"plant","t":"plants","i":["123-124"],"a":0,"b":1}],"405gzo1m7igdjjs":[{"n":"plant","t":"plants","i":["125-126"],"a":0,"b":1}],"405gzo1m7igdjjt":[{"n":"plant","t":"plants","i":["127-128"],"a":0,"b":1}],"405gzo1m7igdjju":[{"n":"plant","t":"plants","i":["129-130"],"a":0,"b":1}],"405gzo1m7igdjjv":[{"n":"plant","t":"plants","i":["131-132"],"a":0,"b":1}],"405gzo1m7igdjjw":[{"n":"plant","t":"plants","i":["133-134"],"a":0,"b":1}],"405gzo1m7igdjjx":[{"n":"plant","t":"plants","i":["135-136"],"a":0,"b":1}],"405gzo1m7igdjjy":[{"n":"plant","t":"plants","i":["137-138"],"a":0,"b":1}],"405gzo1m7igdjjz":[{"n":"plant","t":"plants","i":["139-142"],"a":1,"b":1}],"405gzo1m7igdjk0":[{"n":"plant","t":"plants","i":["143-146"],"a":1,"b":1}],"405gzo1m7igdjk1":[{"n":"plant","t":"plants","i":["147-150"],"a":1,"b":1}],"405gzo1m7igdjk2":[{"n":"plant","t":"plants","i":["151-154"],"a":1,"b":1}],"405gzo1m7igdjk3":[{"n":"plant","t":"plants","i":["155-158"],"a":1,"b":1}],"405gzo1m7igdjk4":[{"n":"plant","t":"plants","i":["159-162"],"a":1,"b":1}],"405gzo1m7igdjk5":[{"n":"plant","t":"plants","i":["163-166"],"a":1,"b":1}],"405gzo1m7igdjk6":[{"n":"plant","t":"plants","i":["167-170"],"a":1,"b":1}],"405gzo1m7igdjk7":[{"n":"plant","t":"plants","i":["171-174"],"a":1,"b":1}],"405gzo1m7igfwle":[{"n":"package","t":"packages","i":["114-115"],"a":0,"b":1}],"405gzo1m7igfwlf":[{"n":"package","t":"packages","i":["116-117"],"a":0,"b":1}],"405gzo1m7igfwlg":[{"n":"package","t":"packages","i":["118-119"],"a":0,"b":1}],"405gzo1m7igfwlh":[{"n":"package","t":"packages","i":["120-121"],"a":0,"b":1}],"405gzo1m7igfwli":[{"n":"package","t":"packages","i":["122-123"],"a":0,"b":1}],"405gzo1m7igfwlj":[{"n":"package","t":"packages","i":["124-126"],"a":0,"b":2}],"405gzo1m7igfwlk":[{"n":"package","t":"packages","i":["127-130"],"a":1,"b":1}],"405gzo1m7igfwll":[{"n":"package","t":"packages","i":["131-134"],"a":1,"b":1}],"405gzo1m7igfwlm":[{"n":"package","t":"packages","i":["135-138"],"a":1,"b":1}],"405gzo1m7igfwln":[{"n":"package","t":"packages","i":["139-140"],"a":0,"b":1}],"405gzo1m7igfwlo":[{"n":"package","t":"packages","i":["141-142"],"a":0,"b":1}],"405gzo1m7igfwlp":[{"n":"package","t":"packages","i":["143-144"],"a":0,"b":1}],"405gzo1m7igfwlq":[{"n":"package","t":"packages","i":["145-146"],"a":0,"b":1}],"405gzo1m7igfwlr":[{"n":"package","t":"packages","i":["147-150"],"a":1,"b":1}],"405gzo1m7igfwls":[{"n":"package","t":"packages","i":["151-154"],"a":1,"b":1}],"405gzo1m7igfwlt":[{"n":"package","t":"packages","i":["155-158"],"a":1,"b":1}],"405gzo1m7igfwlu":[{"n":"package","t":"packages","i":["159-160"],"a":0,"b":1}],"405gzo1m7igfwlv":[{"n":"package","t":"packages","i":["161-162"],"a":0,"b":1}],"405gzo1m7igfwlw":[{"n":"package","t":"packages","i":["163-164"],"a":0,"b":1}],"405gzo1m7igfwlx":[{"n":"package","t":"packages","i":["165-166"],"a":0,"b":1}],"405gzo1m7igfwly":[{"n":"package","t":"packages","i":["167-169"],"a":0,"b":2}],"405gzo1m7igfwlz":[{"n":"package","t":"packages","i":["170-171"],"a":1,"b":0}],"405gzo1m7igfwm0":[{"n":"package","t":"packages","i":["172-173"],"a":0,"b":1}],"405gzo1m7igfwm1":[{"n":"package","t":"packages","i":["174-175"],"a":0,"b":1}],"405gzo1m7igfwm2":[{"n":"package","t":"packages","i":["176-179"],"a":1,"b":1}],"405gzo1m7igfwm3":[{"n":"package","t":"packages","i":["180-183"],"a":1,"b":1}],"405gzo1m7igfwm4":[{"n":"package","t":"packages","i":["184-186"],"a":0,"b":2}],"405gzo1m7igfwm5":[{"n":"package","t":"packages","i":["187-189"],"a":0,"b":2}],"405gzo1m7igfwm6":[{"n":"package","t":"packages","i":["190-193"],"a":1,"b":1}],"405gzo1m7igfwm7":[{"n":"package","t":"packages","i":["194-197"],"a":1,"b":1}],"405gzo1m7igfwm8":[{"n":"package","t":"packages","i":["198-201"],"a":1,"b":1}],"405gzo1m7igfwm9":[{"n":"package","t":"packages","i":["202-205"],"a":1,"b":1}],"405gzo1m7igfwma":[{"n":"package","t":"packages","i":["206-209"],"a":1,"b":1}],"405gzo1m7igfwmb":[{"n":"package","t":"packages","i":["210-213"],"a":1,"b":1}],"405gzo1m7igfwmc":[{"n":"package","t":"packages","i":["214-217"],"a":1,"b":1}],"405gzo1m7igfwmd":[{"n":"package","t":"packages","i":["218-221"],"a":1,"b":1}],"405gzo1m7iggx1a":[{"n":"crafting bench","t":"crafting","i":["0-7"],"a":3,"b":1}],"405gzo1m7ighwx0":[{"n":"tyre","t":"tyres","i":["0-1"],"a":0,"b":1}],"405gzo1m7ighwx1":[{"n":"tyre","t":"tyres","i":["2-5"],"a":1,"b":1}],"405gzo1m7ighwx2":[{"n":"tyre","t":"tyres","i":["6-7"],"a":0,"b":1}],"405gzo1m7ighwx3":[{"n":"tyre","t":"tyres","i":["8-13"],"a":1,"b":2}],"405gzo1m7ighwx4":[{"n":"tyre","t":"tyres","i":["14-17"],"a":0,"b":3}],"405gzo1m7ighwx5":[{"n":"tyre","t":"tyres","i":["18-20"],"a":0,"b":2}],"405gzo1m7ighwx6":[{"n":"tyre","t":"tyres","i":["21-26"],"a":1,"b":2}],"405gzo1m7igj8vm":[{"n":"machine","t":"vending machine","i":["0-5"],"a":1,"b":2}],"405gzo1m7igj8vn":[{"n":"machine","t":"vending machine","i":["6-11"],"a":1,"b":2}],"405gzo1m7igj8vo":[{"n":"machine","t":"vending machine","i":["12-17"],"a":1,"b":2}],"405gzo1m7igj8vp":[{"n":"machine","t":"vending machine","i":["18-23"],"a":1,"b":2}],"405gzo1m7igj8vq":[{"n":"machine","t":"vending machine","i":["24-29"],"a":1,"b":2}],"405gzo1m7igj8vr":[{"n":"machine","t":"vending machine","i":["30-35"],"a":1,"b":2}],"405gzo1m7igj8vs":[{"n":"machine","t":"vending machine","i":["36-41"],"a":1,"b":2}],"405gzo1m7igj8vt":[{"n":"machine","t":"vending machine","i":["42-47"],"a":1,"b":2}],"405gzo1m7igj8vu":[{"n":"machine","t":"vending machine","i":["48-53"],"a":1,"b":2}],"405gzo1m7igj8vv":[{"n":"machine","t":"vending machine","i":["54-59"],"a":1,"b":2}],"405gzo1m7igj8vw":[{"n":"machine","t":"vending machine","i":["60-65"],"a":1,"b":2}],"405gzo1m7igj8vx":[{"n":"machine","t":"vending machine","i":["66-71"],"a":1,"b":2}],"405gzo1m7igj8vy":[{"n":"machine","t":"vending machine","i":["72-77"],"a":1,"b":2}],"405gzo1m7igj8vz":[{"n":"machine","t":"vending machine","i":["78-83"],"a":1,"b":2}],"405gzo1m7igj8w0":[{"n":"machine","t":"vending machine","i":["84-89"],"a":1,"b":2}],"405gzo1m7igkgom":[{"n":"air vent","t":"vents","i":["0-8"],"a":2,"b":2}],"405gzo1m7igkgon":[{"n":"air vent","t":"vents","i":["9-17"],"a":2,"b":2}],"405gzo1m7igkgoo":[{"n":"air vent","t":"vents","i":["18-26"],"a":2,"b":2}],"405gzo1m7igkgop":[{"n":"air vent","t":"vents","i":["27-32"],"a":2,"b":1}],"405gzo1m7igkgoq":[{"n":"air vent","t":"vents","i":["33-36"],"a":1,"b":1}],"405gzo1m7igkgor":[{"n":"air vent","t":"vents","i":["37-40"],"a":1,"b":1}],"405gzo1m7igkgos":[{"n":"air vent","t":"vents","i":["41-46"],"a":2,"b":1}],"405gzo1m7igkgot":[{"n":"air vent","t":"vents","i":["47-50"],"a":1,"b":1}],"405gzo1m7igkgou":[{"n":"air vent","t":"vents","i":["51-54"],"a":1,"b":1}],"405gzo1m7iglj1b":[{"n":"store sign","t":"signs","i":["28-31"],"a":1,"b":1}],"405gzo1m7iglj1c":[{"n":"store sign","t":"signs","i":["32-33"],"a":0,"b":1}],"405gzo1m7iglj1d":[{"n":"store sign","t":"signs","i":["34-35"],"a":0,"b":1}],"405gzo1m7iglj1e":[{"n":"store sign","t":"signs","i":["36-37"],"a":0,"b":1}],"405gzo1m7iglj1f":[{"n":"store sign","t":"signs","i":["38-39"],"a":0,"b":1}],"405gzo1m7iglj1g":[{"n":"store sign","t":"signs","i":["40-43"],"a":1,"b":1}],"405gzo1m7iglj1h":[{"n":"store sign","t":"signs","i":["44-45"],"a":0,"b":1}],"405gzo1m7iglj1i":[{"n":"store sign","t":"signs","i":["46-47"],"a":0,"b":1}],"405gzo1m7iglj1j":[{"n":"store sign","t":"signs","i":["48-49"],"a":0,"b":1}],"405gzo1m7iglj1k":[{"n":"store sign","t":"signs","i":["50-51"],"a":0,"b":1}],"405gzo1m7igmmnc":[{"n":"bench","t":"chairs","i":["12-17"],"a":2,"b":1}],"405gzo1m7igmmnd":[{"n":"bench","t":"chairs","i":["18-23"],"a":2,"b":1}],"405gzo1m7igmmne":[{"n":"bench","t":"chairs","i":["24-27"],"a":0,"b":3}],"405gzo1m7igmmnf":[{"n":"bench","t":"chairs","i":["28-31"],"a":0,"b":3}],"405gzo1m7ignk4m":[{"n":"blockade","t":"blockades","i":["0-3"],"a":1,"b":1}],"405gzo1m7ignk4n":[{"n":"blockade","t":"blockades","i":["4-7"],"a":1,"b":1}],"405gzo1m7ignk4o":[{"n":"blockade","t":"blockades","i":["8-13"],"a":1,"b":2}],"405gzo1m7ignk4p":[{"n":"blockade","t":"blockades","i":["14-19"],"a":1,"b":2}],"405gzo1m7ignk4q":[{"n":"blockade","t":"blockades","i":["20-23"],"a":1,"b":1}],"405gzo1m7ignk4r":[{"n":"blockade","t":"blockades","i":["24-27"],"a":1,"b":1}],"405gzo1m7ignk4s":[{"n":"blockade","t":"blockades","i":["28-31"],"a":1,"b":1}],"405gzo1m7ignk4t":[{"n":"blockade","t":"blockades","i":["32-34"],"a":0,"b":2}],"405gzo1m7ignk4u":[{"n":"blockade","t":"blockades","i":["35-37"],"a":0,"b":2}],"405gzo1m7igo4in":[{"n":"cone","t":"cones","i":["0-1"],"a":0,"b":1}],"405gzo1m7igo4io":[{"n":"cone","t":"cones","i":["2-3"],"a":0,"b":1}],"405gzo1m7igo4ip":[{"n":"cone","t":"cones","i":["4-5"],"a":1,"b":0}],"405gzo1m7igo4iq":[{"n":"cone","t":"cones","i":["6-7"],"a":1,"b":0}],"405gzo1m7igo4ir":[{"n":"cone","t":"cones","i":["8-9"],"a":1,"b":0}],"405gzo1m7igo4is":[{"n":"cone","t":"cones","i":["10-11"],"a":1,"b":0}],"405gzo1m7igpq85":[{"n":"window","t":"windows","i":["920-928"],"a":2,"b":2}],"405gzo1m7igpq86":[{"n":"window","t":"windows","i":["929-937"],"a":2,"b":2}],"405gzo1m7igpq87":[{"n":"window","t":"windows","i":["938-946"],"a":2,"b":2}],"405gzo1m7igpq88":[{"n":"window","t":"windows","i":["947-952"],"a":2,"b":1}],"405gzo1m7igpq89":[{"n":"window","t":"windows","i":["953-958"],"a":2,"b":1}],"405gzo1m7igpq8a":[{"n":"window","t":"windows","i":["959-964"],"a":2,"b":1}],"405gzo1m7igpq8b":[{"n":"window","t":"windows","i":["965-970"],"a":2,"b":1}],"405gzo1m7igpq8c":[{"n":"window","t":"windows","i":["971-976"],"a":2,"b":1}],"405gzo1m7igpq8d":[{"n":"window","t":"windows","i":["977-982"],"a":2,"b":1}],"405gzo1m7igpq8e":[{"n":"window","t":"windows","i":["983-988"],"a":2,"b":1}],"405gzo1m7igpq8f":[{"n":"window","t":"windows","i":["989-994"],"a":2,"b":1}],"405gzo1m7igpq8g":[{"n":"window","t":"windows","i":["995-1000"],"a":2,"b":1}],"405gzo1m7igpq8h":[{"n":"window","t":"windows","i":["1001-1006"],"a":2,"b":1}],"405gzo1m7igpq8i":[{"n":"window","t":"windows","i":["1007-1012"],"a":2,"b":1}],"405gzo1m7igqghe":[{"n":"door","t":"door","i":["188-196"],"a":2,"b":2}],"405gzo1m7igqghf":[{"n":"door","t":"door","i":["197-205"],"a":2,"b":2}],"405gzo1m7igqghg":[{"n":"door","t":"door","i":["206-214"],"a":2,"b":2}],"405gzo1m7igqghh":[{"n":"door","t":"door","i":["215-223"],"a":2,"b":2}],"405gzo1m7igqghi":[{"n":"door","t":"door","i":["224-232"],"a":2,"b":2}],"405gzo1m7igqghj":[{"n":"door","t":"door","i":["233-241"],"a":2,"b":2}],"405gzo1m7igqghk":[{"n":"door","t":"door","i":["242-256"],"a":4,"b":2}],"405gzo1m7igqghl":[{"n":"door","t":"door","i":["257-271"],"a":4,"b":2}],"405gzo1m7igx7yr":[{"n":"frame","t":"house_frame","i":["0-62"],"a":6,"b":8}],"405gzo1m7igx7yy":[{"n":"frame","t":"house_frame","i":["63-125"],"a":6,"b":8}],"405gzo1m7igx7z4":[{"n":"frame","t":"house_frame","i":["126-245"],"a":11,"b":9}],"405gzo1m7igx7z9":[{"n":"frame","t":"house_frame","i":["246-365"],"a":11,"b":9}],"405gzo1m7igx7zf":[{"n":"frame","t":"house_frame","i":["366-497"],"a":11,"b":10}],"405gzo1m7igx7zi":[{"n":"frame","t":"house_frame","i":["498-596"],"a":8,"b":10}],"405gzo1m7igx7zm":[{"n":"frame","t":"house_frame","i":["597-695"],"a":8,"b":10}],"405gzo1m7igx7zr":[{"n":"frame","t":"house_frame","i":["696-794"],"a":8,"b":10}],"405gzo1m7igx7zu":[{"n":"frame","t":"house_frame","i":["795-893"],"a":8,"b":10}],"405gzo1m7igx7zz":[{"n":"frame","t":"house_frame","i":["894-913"],"a":3,"b":4}],"405gzo1m7igx801":[{"n":"frame","t":"house_frame","i":["914-933"],"a":3,"b":4}],"405gzo1m7igx802":[{"n":"frame","t":"house_frame","i":["934-953"],"a":3,"b":4}],"405gzo1m7igx803":[{"n":"frame","t":"house_frame","i":["954-973"],"a":3,"b":4}],"405gzo1m7igx804":[{"n":"frame","t":"house_frame","i":["974-993"],"a":3,"b":4}],"405gzo1m7igx805":[{"n":"frame","t":"house_frame","i":["994-1013"],"a":3,"b":4}],"405gzo1m7igx806":[{"n":"frame","t":"house_frame","i":["1014-1033"],"a":3,"b":4}],"405gzo1m7igx80a":[{"n":"frame","t":"house_frame","i":["1034-1053"],"a":3,"b":4}],"405gzo1m7igx80b":[{"n":"frame","t":"house_frame","i":["1054-1073"],"a":3,"b":4}],"405gzo1m7igx80c":[{"n":"frame","t":"house_frame","i":["1074-1093"],"a":3,"b":4}],"405gzo1m7igx80d":[{"n":"frame","t":"house_frame","i":["1094-1113"],"a":3,"b":4}],"405gzo1m7igx80e":[{"n":"frame","t":"house_frame","i":["1114-1133"],"a":3,"b":4}],"405gzo1m7igx80f":[{"n":"frame","t":"house_frame","i":["1134-1153"],"a":3,"b":4}],"405gzo1m7igx80g":[{"n":"frame","t":"house_frame","i":["1154-1173"],"a":3,"b":4}],"405gzo1m7igx80h":[{"n":"frame","t":"house_frame","i":["1174-1193"],"a":3,"b":4}],"405gzo1m7igx80i":[{"n":"frame","t":"house_frame","i":["1194-1213"],"a":3,"b":4}],"405gzo1m7igx80j":[{"n":"frame","t":"house_frame","i":["1214-1258"],"a":8,"b":4}],"405gzo1m7igx80l":[{"n":"frame","t":"house_frame","i":["1259-1303"],"a":8,"b":4}],"405gzo1m7igx80n":[{"n":"frame","t":"house_frame","i":["1304-1348"],"a":8,"b":4}],"405gzo1m7igx80r":[{"n":"frame","t":"house_frame","i":["1349-1393"],"a":8,"b":4}],"405gzo1m7igx80t":[{"n":"frame","t":"house_frame","i":["1394-1438"],"a":8,"b":4}],"405gzo1m7igx80u":[{"n":"frame","t":"house_frame","i":["1439-1483"],"a":8,"b":4}],"405gzo1m7igx80y":[{"n":"frame","t":"house_frame","i":["1484-1528"],"a":8,"b":4}],"405gzo1m7igx80z":[{"n":"frame","t":"house_frame","i":["1529-1573"],"a":8,"b":4}],"405gzo1m7igx810":[{"n":"frame","t":"house_frame","i":["1574-1618"],"a":8,"b":4}],"405gzo1m7igx816":[{"n":"frame","t":"house_frame","i":["1619-1663"],"a":8,"b":4}],"405gzo1m7igx817":[{"n":"frame","t":"house_frame","i":["1664-1708"],"a":8,"b":4}],"405gzo1m7igx819":[{"n":"frame","t":"house_frame","i":["1709-1753"],"a":8,"b":4}],"405gzo1m7igx81a":[{"n":"frame","t":"house_frame","i":["1754-1767"],"a":6,"b":1}],"405gzo1m7igx81b":[{"n":"frame","t":"house_frame","i":["1768-1781"],"a":6,"b":1}],"405gzo1m7igx81g":[{"n":"frame","t":"house_frame","i":["1782-1826"],"a":8,"b":4}],"405gzo1m7igx81h":[{"n":"frame","t":"house_frame","i":["1827-1871"],"a":8,"b":4}],"405gzo1m7igx81i":[{"n":"frame","t":"house_frame","i":["1872-1885"],"a":6,"b":1}],"405gzo1m7igx81j":[{"n":"frame","t":"house_frame","i":["1886-1930"],"a":8,"b":4}],"405gzo1m7igx81k":[{"n":"frame","t":"house_frame","i":["1931-1944"],"a":6,"b":1}],"405gzo1m7igx81o":[{"n":"frame","t":"house_frame","i":["1945-1958"],"a":6,"b":1}],"405gzo1m7igx81p":[{"n":"frame","t":"house_frame","i":["1959-1988"],"a":4,"b":5}],"405gzo1m7igx81q":[{"n":"frame","t":"house_frame","i":["1989-2018"],"a":4,"b":5}],"405gzo1m7igx81s":[{"n":"frame","t":"house_frame","i":["2019-2048"],"a":4,"b":5}],"405gzo1m7igx81t":[{"n":"frame","t":"house_frame","i":["2049-2078"],"a":4,"b":5}],"405gzo1m7igx820":[{"n":"frame","t":"house_frame","i":["2079-2108"],"a":4,"b":5}],"405gzo1m7igx821":[{"n":"frame","t":"house_frame","i":["2109-2138"],"a":4,"b":5}],"405gzo1m7igx822":[{"n":"frame","t":"house_frame","i":["2139-2168"],"a":4,"b":5}],"405gzo1m7igx823":[{"n":"frame","t":"house_frame","i":["2169-2198"],"a":4,"b":5}],"405gzo1m7igx824":[{"n":"frame","t":"house_frame","i":["2199-2228"],"a":4,"b":5}],"405gzo1m7igx826":[{"n":"frame","t":"house_frame","i":["2229-2258"],"a":4,"b":5}],"405gzo1m7igx827":[{"n":"frame","t":"house_frame","i":["2259-2288"],"a":4,"b":5}],"405gzo1m7igx828":[{"n":"frame","t":"house_frame","i":["2289-2318"],"a":4,"b":5}],"405gzo1m7igx829":[{"n":"frame","t":"house_frame","i":["2319-2348"],"a":4,"b":5}],"405gzo1m7igx82a":[{"n":"frame","t":"house_frame","i":["2349-2378"],"a":4,"b":5}],"405gzo1m7igx82c":[{"n":"frame","t":"house_frame","i":["2379-2408"],"a":4,"b":5}],"405gzo1m7igx82d":[{"n":"frame","t":"house_frame","i":["2409-2438"],"a":4,"b":5}],"405gzo1m7igx82e":[{"n":"frame","t":"house_frame","i":["2439-2468"],"a":4,"b":5}],"405gzo1m7igx82f":[{"n":"frame","t":"house_frame","i":["2469-2498"],"a":4,"b":5}],"405gzo1m7igx82g":[{"n":"frame","t":"house_frame","i":["2499-2528"],"a":4,"b":5}],"405gzo1m7igx82l":[{"n":"frame","t":"house_frame","i":["2529-2558"],"a":4,"b":5}],"405gzo1m7igx82o":[{"n":"frame","t":"house_frame","i":["2559-2588"],"a":4,"b":5}],"405gzo1m7igx82p":[{"n":"frame","t":"house_frame","i":["2589-2618"],"a":4,"b":5}],"405gzo1m7igx82q":[{"n":"frame","t":"house_frame","i":["2619-2648"],"a":4,"b":5}],"405gzo1m7igx82r":[{"n":"frame","t":"house_frame","i":["2649-2678"],"a":4,"b":5}],"405gzo1m7igxqui":[{"n":"frame","t":"house_frame","i":["2679-2718"],"a":7,"b":4}],"405gzo1m7igxquj":[{"n":"frame","t":"house_frame","i":["2719-2750"],"a":3,"b":7}],"405gzo1m7igxquk":[{"n":"frame","t":"house_frame","i":["2751-2762"],"a":2,"b":3}],"405gzo1m7jgsr2f":[{"n":"logo","t":"graphics","i":["0-44"],"a":14,"b":2}],"405gzo1m7jqvrcf":[{"n":"logo_outline","t":"graphics","i":["45-89"],"a":14,"b":2}]}